flask_json_resource
