Metadata-Version: 1.0
Name: flask-json-resource
Version: 0.2.18
Summary: UNKNOWN
Home-page: UNKNOWN
Author: Ernst Odolphi
Author-email: ernst.odolphi@gmail.com
License: UNKNOWN
Platform: UNKNOWN
